LICENSE
MANIFEST.in
README.md
pyproject.toml
requirements.txt
setup.cfg
setup.py
src/LZGraphs/__init__.py
src/LZGraphs.egg-info/PKG-INFO
src/LZGraphs.egg-info/SOURCES.txt
src/LZGraphs.egg-info/dependency_links.txt
src/LZGraphs.egg-info/requires.txt
src/LZGraphs.egg-info/top_level.txt
src/LZGraphs/BagOfWords/BOWEncoder.py
src/LZGraphs/BagOfWords/__init__.py
src/LZGraphs/Graphs/AminoAcidPositional.py
src/LZGraphs/Graphs/LZGraphBase.py
src/LZGraphs/Graphs/Naive.py
src/LZGraphs/Graphs/NucleotideDoublePositional.py
src/LZGraphs/Graphs/__init__.py
src/LZGraphs/Metircs/Metrics.py
src/LZGraphs/Metircs/__init__.py
src/LZGraphs/Mixins/GeneLogicMixin.py
src/LZGraphs/Mixins/GenePredictionMixin.py
src/LZGraphs/Mixins/RandomWalkMixin.py
src/LZGraphs/Mixins/__init__.py
src/LZGraphs/Utilities/NodeEdgeSaturationProbe.py
src/LZGraphs/Utilities/Utilities.py
src/LZGraphs/Utilities/__init__.py
src/LZGraphs/Utilities/decomposition.py
src/LZGraphs/Utilities/graph_operations.py
src/LZGraphs/Utilities/misc.py
src/LZGraphs/Visualization/Visualize.py
src/LZGraphs/Visualization/__init__.py
tests/TestModule.py