Metadata-Version: 2.2
Name: LZGraphs
Version: 1.1.1
Summary: An Implementation of LZ76 Based Graphs for Repertoire Representation and Analysis 
Home-page: https://github.com/MuteJester/LZGraphs
Download-URL: https://github.com/MuteJester/LZGraphs/archive/refs/tags/Beta1.1.1.tar.gz
Author: Thomas Konstantinovsky
Author-email: thomaskon90@gmail.com
License: MIT
Keywords: Graph Theory,Immunology,Analytics,Biology,T-cell,Repertoire,CDR3
Classifier: Development Status :: 3 - Alpha
Classifier: Intended Audience :: Developers
Classifier: Intended Audience :: Science/Research
Classifier: Topic :: Scientific/Engineering :: Bio-Informatics
Classifier: Topic :: Scientific/Engineering :: Information Analysis
Classifier: License :: OSI Approved :: MIT License
Classifier: Programming Language :: Python :: 3
Classifier: Programming Language :: Python :: 3.8
Classifier: Programming Language :: Python :: 3.9
Classifier: Programming Language :: Python :: 3.10
Classifier: Operating System :: OS Independent
Requires-Python: >=3.8, <4
License-File: LICENSE
Requires-Dist: networkx~=3.1
Requires-Dist: numpy~=1.24.3
Requires-Dist: pandas~=1.5.3
Requires-Dist: tqdm~=4.65.0
Requires-Dist: matplotlib~=3.7.2
Requires-Dist: seaborn~=0.12.2
Requires-Dist: setuptools~=69.5.1
Dynamic: author
Dynamic: author-email
Dynamic: classifier
Dynamic: description
Dynamic: description-content-type
Dynamic: download-url
Dynamic: home-page
Dynamic: keywords
Dynamic: license
Dynamic: requires-dist
Dynamic: requires-python
Dynamic: summary
